pyvjoy/__init__.py
pyvjoy/_sdk.py
pyvjoy/constants.py
pyvjoy/exceptions.py
pyvjoy/vjoydevice.py
pyvjoy/lib/x64/vJoyInterface.dll
pyvjoy/lib/x86/vJoyInterface.dll
pyvjoyffb-0.4.dist-info/METADATA
pyvjoyffb-0.4.dist-info/WHEEL
pyvjoyffb-0.4.dist-info/top_level.txt
pyvjoyffb-0.4.dist-info/RECORD
