Metadata-Version: 2.4
Name: pyvjoyffb
Version: 0.4
Summary: Python bindings for vJoy with full force feedback support
Author: Yannick Richter
Project-URL: Homepage, https://github.com/Ultrawipf/pyvjoy
Classifier: Programming Language :: Python :: 3
Classifier: License :: OSI Approved :: MIT License
Classifier: Operating System :: Microsoft :: Windows
Requires-Python: >=3.8
